Metadata-Version: 1.1
Name: igdbapi
Version: 0.2
Summary: An object-oriented Python 2.7+ library for accessing the Igdb API
Home-page: https://github.com/noragami/igdbapi
Author: noragami
Author-email: yuumeikai@gmail.com
License: MIT
Download-URL: https://github.com/noragami/igdbapi/tarball/0.2
Keywords: igdb,api,games
Platform: UNKNOWN
